[

  {
    "TrackID": 1917,
    "Artist": "Queen",
    "TrackName": "I Want It All - 2011 Remaster",
    "Album": "Greatest Hits II",
    "SpotifyUri": "spotify:track:59CsbfwLNCAUGbBQV3Tki4",
    "LastFmLink": "http://www.last.fm/music/Queen/_/I+Want+It+All+-+2011+Remaster",
    "Length": null,
    "PictureSmall": "http://userserve-ak.last.fm/serve/34s/57090809.png",
    "PictureMedium": "http://userserve-ak.last.fm/serve/64s/57090809.png",
    "PictureLarge": "http://userserve-ak.last.fm/serve/126/57090809.png",
    "PictureExtraLarge": "http://userserve-ak.last.fm/serve/300x300/66082664.png",
    "DateAdded": "2012-01-12T10:28:27.423",
    "Likes": 4,
    "Dislikes": 1,
    "PlayCount": 3,
    "LastPlayed": "2012-10-01T10:46:29.39",
    "RequestDate": null,
    "RequestUserID": null,
    "TrackLikes": [
      {
        "Name": "autoplay",
        "UserID": 1,
        "IsLike": true
      },
      {
        "Name": "Tom Chittock",
        "UserID": 223606535,
        "IsLike": true
      },
      {
        "Name": "Gavin Harris",
        "UserID": 514670242,
        "IsLike": false
      },
      {
        "Name": "Ben Lane",
        "UserID": 591615411,
        "IsLike": true
      },
      {
        "Name": "Ben Richardson",
        "UserID": 670665321,
        "IsLike": true
      }
    ]
  }
]